{
    "r88rData" : [
        {
        "headline":
            "Geology",
        "url":
            "http://v3.api.r88r.net/v3/headlines?cname=V3A.geology",
        "img":{"src":
            "/assets/images/Cool_Geological_Layering.jpg"}
        },
        {
        "headline":
            "Climate",
        "url":
            "http://v3.api.r88r.net/v3/headlines?cname=V3A.climate",
        "img":{"src":
            "/assets/images/cloud-cover-climate.jpg"}
        },
        {
        "headline":
            "Energy",
        "url":
            "http://v3.api.r88r.net/v3/headlines?cname=V3A.energy",
        "img":{"src":
            "/assets/images/energy-feed.jpg"}
        },
        {
        "headline":
            "Government",
        "url":
            "http://v3.api.r88r.net/v3/headlines?cname=V3A.government",
        "img":{"src":
            "/assets/images/capitoldomeban.jpg"}
        },
        {
        "headline":
            "Landscape",
        "url":
            "http://v3.api.r88r.net/v3/headlines?cname=V3A.landscape",
        "img":{"src":
            "/assets/images/1024px-Balaton_Hungary_Landscape.jpg"}
        },
        {
        "headline":
            "Math",
        "url":
            "http://v3.api.r88r.net/v3/headlines?cname=V3A.math",
        "img":{"src":
            "/assets/images/1011math.jpg"}
        },
        {
        "headline":
            "Oceans",    
        "url":
            "http://v3.api.r88r.net/v3/headlines?cname=V3A.oceans",
        "img":{"src":
            "/assets/images/Atlantic-Ocean.jpg"}
        },
        {
        "headline":
            "Architecture ",
        "url":
            "http://v3.api.r88r.net/v3/headlines?cname=V3A.architecture",
        "img":{"src":
            "/assets/images/lacubo01.jpg"}
        },
        {
        "headline":
            "Bioinformatics",
        "url":
            "http://v3.api.r88r.net/v3/headlines?cname=V3A.bioinformatics",
        "img":{"src":
            "/assets/images/cropped-dna.jpg"}
        },
        {
        "headline":
            "Education",
        "url":
            "http://v3.api.r88r.net/v3/headlines?cname=V3A.education",
        "img":{"src":
            "/assets/images/6357758756001800821152486765_State-Education---Generic-jpg.jpg"}
        },
        {
        "headline":
            "Education Policy",
        "url":
            "http://v3.api.r88r.net/v3/headlines?cname=V3A.educationpolicy",
        "img":{"src":
            "/assets/images/pencilgraphdown_jpg_800x1000_q100.jpg"}
        },
        {
        "headline":
            "Electric Vehicles",
        "url":
            "http://v3.api.r88r.net/v3/headlines?cname=V3A.electricvehicles",
        "img":{"src":
            "/assets/images/electric-car-electric-vechile-EV.jpg"}
        },
        {
        "headline":
            "Local Food",
        "url":
            "http://v3.api.r88r.net/v3/headlines?cname=V3A.localfood",
        "img":{"src":
            "/assets/images/local-food (1).jpg"}
        },
        {
        "headline":
            "Architecture",
        "url":
            "http://v3.api.r88r.net/v3/headlines?cname=V3A.architecture",
        "img":{"src":
            "/assets/images/lacubo01.jpg"}
        },
        {
        "headline":
            "Automotive",
        "url":
            "http://v3.api.r88r.net/v3/headlines?cname=V3A.automotive",
        "img":{"src":
            "/assets/images/sap-erp-automotive.jpg"}
        },
        {
        "headline":
            "Buddhism",
        "url":
            "http://v3.api.r88r.net/v3/headlines?cname=V3A.buddhism",
        "img":{"src":
            "/assets/images/buddhism-feed.jpg"}
        },
        {
        "headline":
            "Careers",
        "url":
            "http://v3.api.r88r.net/v3/headlines?cname=V3A.careers",
        "img":{"src":
            "/assets/images/palyavalasztas.png"}
        },
        {
        "headline":
            "Chefs",
        "url":
            "http://v3.api.r88r.net/v3/headlines?cname=V3A.chefs",
        "img":{"src":
            "/assets/images/pic-12.jpg"}
        },
        {
        "headline":
            "Culture",
        "url":
            "http://v3.api.r88r.net/v3/headlines?cname=V3A.culture",
        "img":{"src":
            "/assets/images/flags_world.jpg"}
        },
        {
        "headline":
            "Dairy",
        "url":
            "http://v3.api.r88r.net/v3/headlines?cname=V3A.dairy",
        "img":{"src":
            "/assets/images/dairy-fat-study-image.jpeg"}
        },
        {
        "headline":
            "Environment",
        "url":
            "http://v3.api.r88r.net/v3/headlines?cname=V3A.environment",
        "img":{"src":
            "/assets/images/environment-feed.jpg"}
        },
        {
        "headline":
            "Farming",
        "url":
            "http://v3.api.r88r.net/v3/headlines?cname=V3A.farming",
        "img":{"src":
            "/assets/images/Farm-Equipment.jpg"}
        },
        {
        "headline":
            "Gardening",
        "url":
            "http://v3.api.r88r.net/v3/headlines?cname=V3A.gardening",
        "img":{"src":
            "/assets/images/gardening-001-640x320.jpg"}
        },
        {
        "headline":
            "Green Home",
        "url":
            "http://v3.api.r88r.net/v3/headlines?cname=V3A.greenhome",
        "img":{"src":
            "/assets/images/green-home-designs-550x388-on-home-designfantastic.jpg"}
        },
        {
        "headline":
            "Herbal",
        "url":
            "http://v3.api.r88r.net/v3/headlines?cname=V3A.herbal",
        "img":{"src":
            "/assets/images/Adrenal_Fatigue_herbal_therapy.png"}
        },
        {
        "headline":
            "Immigration",
        "url":
            "http://v3.api.r88r.net/v3/headlines?cname=V3A.immigration",
        "img":{"src":
            "/assets/images/keep-families-together.jpg"}
        },
        {
        "headline":
            "Jazz",
        "url":
            "http://v3.api.r88r.net/v3/headlines?cname=V3A.jazz",
        "img":{"src":
            "/assets/images/480x374xsatchmo-club-hangover-e1367196787338.jpg.pagespeed.ic.ycQr0BFuvN.jpg"}
        },
        {
        "headline":
            "Oil",
        "url":
            "http://v3.api.r88r.net/v3/headlines?cname=V3A.oil",
        "img":{"src":
            "/assets/images/oil-feed.jpg"}
        },
        {
        "headline":
            "Organic Gardening",
        "url":
            "http://v3.api.r88r.net/v3/headlines?cname=V3A.organicgardening",
        "img":{"src":
            "/assets/images/full-size.jpg"}
        },
        {
        "headline":
            "Biodiversity",
        "url":
            "http://v3.api.r88r.net/v3/headlines?cname=V3A.biodiversity",
        "img":{"src":
            "/assets/images/biodiversity_438x0_scale.jpg"}
        },
        {
        "headline":
            "Progressive",
        "url":
            "http://v3.api.r88r.net/v3/headlines?cname=V3A.progressive",
        "img":{"src":
            "/assets/images/131527463_640.jpg"}
        },
        {
        "headline":
            "Rain Forest",
        "url":
            "http://v3.api.r88r.net/v3/headlines?cname=V3A.rainforest",
        "img":{"src":
            "/assets/images/iStock_000013346231Small(2)_ZqCncpxyzB_l.png"}
        },
        {
        "headline":
            "Startups",
        "url":
            "http://v3.api.r88r.net/v3/headlines?cname=V3A.startups",
        "img":{"src":
            "/assets/images/video.yahoofinance.com@a3be196f-5e8c-32ba-a533-dfb288d4962c_FULL.jpg"}
        },
        {
        "headline":
            "Transportation",
        "url":
            "http://v3.api.r88r.net/v3/headlines?cname=V3A.transportation",
        "img":{"src":
            "/assets/images/RapidTransit1.png"}
        },
        {
        "headline":
            "Transportation",
        "url":
            "http://v3.api.r88r.net/v3/headlines?cname=V3A.transportation",
        "img":{"src":
            "/assets/images/RapidTransit1.png"}
        },
        {
        "headline":
            "Transportation",
        "url":
            "http://v3.api.r88r.net/v3/headlines?cname=V3A.transportation",
        "img":{"src":
            "/assets/images/RapidTransit1.png"}
        },
        {
        "headline":
            "Transportation",
        "url":
            "http://v3.api.r88r.net/v3/headlines?cname=V3A.transportation",
        "img":{"src":
            "/assets/images/RapidTransit1.png"}
        },
        {
        "headline":
            "Transportation",
        "url":
            "http://v3.api.r88r.net/v3/headlines?cname=V3A.transportation",
        "img":{"src":
            "/assets/images/RapidTransit1.png"}
        },
        {
        "headline":
            "Transportation",
        "url":
            "http://v3.api.r88r.net/v3/headlines?cname=V3A.transportation",
        "img":{"src":
            "/assets/images/RapidTransit1.png"}
        },
        {
        "headline":
            "Transportation",
        "url":
            "http://v3.api.r88r.net/v3/headlines?cname=V3A.transportation",
        "img":{"src":
            "/assets/images/RapidTransit1.png"}
        },
        {
        "headline":
            "Transportation",
        "url":
            "http://v3.api.r88r.net/v3/headlines?cname=V3A.transportation",
        "img":{"src":
            "/assets/images/RapidTransit1.png"}
        },
        {
        "headline":
            "Transportation",
        "url":
            "http://v3.api.r88r.net/v3/headlines?cname=V3A.transportation",
        "img":{"src":
            "/assets/images/RapidTransit1.png"}
        },
        {
        "headline":
            "Transportation",
        "url":
            "http://v3.api.r88r.net/v3/headlines?cname=V3A.transportation",
        "img":{"src":
            "/assets/images/RapidTransit1.png"}
        }
    ],
    "feeds" :
    [
        "http://v3.api.r88r.net/v3/headlines?cname=V3A.geology",
        "http://v3.api.r88r.net/v3/headlines?cname=V3A.climate",
        "http://v3.api.r88r.net/v3/headlines?cname=V3A.energy",
        "http://v3.api.r88r.net/v3/headlines?cname=V3A.government",
        "http://v3.api.r88r.net/v3/headlines?cname=V3A.landscape",
        "http://v3.api.r88r.net/v3/headlines?cname=V3A.math",
        "http://v3.api.r88r.net/v3/headlines?cname=V3A.oceans",

        "http://v3.api.r88r.net/v3/headlines?cname=V3A.architecture",
        "http://v3.api.r88r.net/v3/headlines?cname=V3A.bioinformatics",
        "http://v3.api.r88r.net/v3/headlines?cname=V3A.education",
        "http://v3.api.r88r.net/v3/headlines?cname=V3A.educationpolicy",
        "http://v3.api.r88r.net/v3/headlines?cname=V3A.electricvehicles",
        "http://v3.api.r88r.net/v3/headlines?cname=V3A.localfood",
        "http://v3.api.r88r.net/v3/headlines?cname=V3A.architecture",

        "http://v3.api.r88r.net/v3/headlines?cname=V3A.automotive",
        "http://v3.api.r88r.net/v3/headlines?cname=V3A.biodiversity",
        "http://v3.api.r88r.net/v3/headlines?cname=V3A.buddhism",
        "http://v3.api.r88r.net/v3/headlines?cname=V3A.careers",
        "http://v3.api.r88r.net/v3/headlines?cname=V3A.chefs",
        "http://v3.api.r88r.net/v3/headlines?cname=V3A.culture",
        "http://v3.api.r88r.net/v3/headlines?cname=V3A.dairy",

        "http://v3.api.r88r.net/v3/headlines?cname=V3A.environment",
        "http://v3.api.r88r.net/v3/headlines?cname=V3A.farming",
        "http://v3.api.r88r.net/v3/headlines?cname=V3A.gardening",
        "http://v3.api.r88r.net/v3/headlines?cname=V3A.greenhome",
        "http://v3.api.r88r.net/v3/headlines?cname=V3A.herbal",
        "http://v3.api.r88r.net/v3/headlines?cname=V3A.immigration",
        "http://v3.api.r88r.net/v3/headlines?cname=V3A.jazz",

        "http://v3.api.r88r.net/v3/headlines?cname=V3A.oil",
        "http://v3.api.r88r.net/v3/headlines?cname=V3A.organicgardening",
        "http://v3.api.r88r.net/v3/headlines?cname=V3A.progressive",
        "http://v3.api.r88r.net/v3/headlines?cname=V3A.rainforest",
        "http://v3.api.r88r.net/v3/headlines?cname=V3A.science",
        "http://v3.api.r88r.net/v3/headlines?cname=V3A.startups",
        "http://v3.api.r88r.net/v3/headlines?cname=V3A.transportation"
    ],
        "preLoadedSpheres" :
        [
        {
            "src":"/assets/images/cryosphere.png",
            "sphereName": "Cryosphere"
        } ,
        {
            "src":"/assets/images/atmosphere.png",
            "sphereName": "Atmosphere"
        } ,
        {
            "src":"/assets/images/forests.png",
            "sphereName": "Forest"
        } , 
        {
            "src":"/assets/images/pollution.png",
            "sphereName": "Pollution"
        } , 
        {
            "src":"/assets/images/agriculture.png",
            "sphereName": "Agriculture"
        } , 
        {
            "src":"/assets/images/education.png",
            "sphereName": "Education"
        } , 
        {
            "src":"/assets/images/built-env.png",
            "sphereName": "Built Environment"
        } , 
        {
            "src":"/assets/images/energy.png",
            "sphereName": "Energy"
        } ,
        {
            "src":"/assets/images/oceans.png",
            "sphereName": "Hydrosphere"
        } ,
        {
            "src":"/assets/images/alt_pol_sphereFIN.png",
            "sphereName": "Alt-Politics"
        } 
    ]



}
